{"resultscore1": "", "resultscore2": "", "resultplayer1": "", "resultplayer2": "", "com1": "VodkaGobalsky", "com2": "Riz0ne", "soc1": "@liquidgobalsky", "soc2": "@superloreboys", "round": "", "p1Team": "", "p2Team": "", "p1Name": "Hokuto", "p2Name": "Cvital", "p1Country": "US", "p2Country": "US", "p1Score": "0", "p2Score": "0", "nextteam1": "", "nextplayer1": "", "nextteam2": "", "nextplayer2": "", "nextcountry1": "", "nextcountry2": "", "timestamp": 1772870939248, "maxScore": "99", "nextRound": ""}